liblaf/actions/__init__.py
liblaf/actions/__init__.pyi
liblaf/actions/_inputs.py
liblaf/actions/_run.py
liblaf/actions/_version.py
liblaf/actions/_version.pyi
liblaf/actions/py.typed
liblaf/actions/actions/__init__.py
liblaf/actions/actions/__init__.pyi
liblaf/actions/actions/release/__init__.py
liblaf/actions/actions/release/__init__.pyi
liblaf/actions/actions/release/_client.py
liblaf/actions/actions/release/_inputs.py
liblaf/actions/actions/release/_main.py
liblaf/actions/actions/review/__init__.py
liblaf/actions/actions/review/__init__.pyi
liblaf/actions/actions/review/_inputs.py
liblaf/actions/actions/review/_main.py
liblaf/actions/actions/ruleset_import/__init__.py
liblaf/actions/actions/ruleset_import/__init__.pyi
liblaf/actions/actions/ruleset_import/_inputs.py
liblaf/actions/actions/ruleset_import/_main.py
liblaf/actions/core/__init__.py
liblaf/actions/core/__init__.pyi
liblaf/actions/core/_core.py
liblaf/actions/github/__init__.py
liblaf/actions/github/__init__.pyi
liblaf/actions/github/_app.py
liblaf/actions/github/_github.py
liblaf/actions/utils/__init__.py
liblaf/actions/utils/__init__.pyi
liblaf/actions/utils/_action.py
liblaf/actions/utils/_logging.py
liblaf/actions/utils/_subprocess.py
liblaf/actions/utils/_text.py
liblaf/actions/utils/cksum/__init__.py
liblaf/actions/utils/cksum/__init__.pyi
liblaf/actions/utils/cksum/_constants.py
liblaf/actions/utils/cksum/_hashsum.py
liblaf/actions/utils/cksum/_sumfile.py
liblaf/actions/utils/cksum/filename.py
liblaf_actions-0.1.8.dist-info/METADATA
liblaf_actions-0.1.8.dist-info/WHEEL
liblaf_actions-0.1.8.dist-info/entry_points.txt
liblaf_actions-0.1.8.dist-info/licenses/LICENSE
liblaf_actions-0.1.8.dist-info/RECORD
