Metadata-Version: 2.4
Name: liblaf-actions
Version: 0.1.8
Summary: Add your description here
Project-URL: Changelog, https://github.com/liblaf/actions/blob/main/CHANGELOG.md
Project-URL: Documentation, https://liblaf.github.io/actions/
Project-URL: Homepage, https://github.com/liblaf/actions
Project-URL: Issue Tracker, https://github.com/liblaf/actions/issues
Project-URL: Release Notes, https://github.com/liblaf/actions/releases
Project-URL: Source Code, https://github.com/liblaf/actions
Author-email: liblaf <30631553+liblaf@users.noreply.github.com>
License-Expression: MIT
License-File: LICENSE
Classifier: Development Status :: 4 - Beta
Classifier: Intended Audience :: Developers
Classifier: License :: OSI Approved
Classifier: License :: OSI Approved :: MIT License
Classifier: Operating System :: OS Independent
Classifier: Programming Language :: Python
Classifier: Programming Language :: Python :: 3
Classifier: Programming Language :: Python :: 3.12
Classifier: Programming Language :: Python :: 3.13
Classifier: Typing :: Typed
Requires-Python: >=3.12
Requires-Dist: environs<15,>=14.1.1
Requires-Dist: githubkit[auth-app]<0.13,>=0.12.13
Requires-Dist: httpx<0.29,>=0.28.1
Requires-Dist: lazy-loader<0.5,>=0.4
Requires-Dist: liblaf-grapes<0.3,>=0.2
Requires-Dist: loguru<0.8,>=0.7.3
Requires-Dist: pydantic-settings<3,>=2.9.1
Requires-Dist: pydantic<3,>=2.11.4
Requires-Dist: rich<15,>=14.0.0
Requires-Dist: tenacity<10,>=9.1.2
